ftp_himawari8_hsd/__init__.py
ftp_himawari8_hsd/ftp_himawari8_hsd.py
ftp_himawari8_hsd-1.1.5.dist-info/LICENSE.txt
ftp_himawari8_hsd-1.1.5.dist-info/METADATA
ftp_himawari8_hsd-1.1.5.dist-info/WHEEL
ftp_himawari8_hsd-1.1.5.dist-info/top_level.txt
ftp_himawari8_hsd-1.1.5.dist-info/RECORD
