Metadata-Version: 2.1
Name: ftp-himawari8-hsd
Version: 1.1.5
Summary: Sateliite Imagery Download Package
Home-page: https://github.com/gSasikala/Python_JAXA_Himawari8_Imagery_Downloader.git
Author: Sasikala Gnanamuthu
Author-email: serskg@nus.edu.sg
License: UNKNOWN
Platform: UNKNOWN
Classifier: Programming Language :: Python :: 3
Classifier: License :: OSI Approved :: MIT License
Classifier: Operating System :: OS Independent
License-File: LICENSE.txt
Requires-Dist: argparse (==1.4.0)
Requires-Dist: dateparser (==1.0.0)
Requires-Dist: DateTime (==4.3)
Requires-Dist: wget (==3.2)
Requires-Dist: bz2file (==0.98)
Requires-Dist: python-dateutil (==2.8.1)
Requires-Dist: pathlib (==1.0.1)
Requires-Dist: regex (==2020.11.13)
Requires-Dist: futures3 (==1.0.0)
Requires-Dist: pandas (~=1.2.4)
Requires-Dist: pytz
